py_hangman/__init__.py
py_hangman/hangman.py
py_hangman-0.4.dist-info/DESCRIPTION.rst
py_hangman-0.4.dist-info/METADATA
py_hangman-0.4.dist-info/RECORD
py_hangman-0.4.dist-info/WHEEL
py_hangman-0.4.dist-info/entry_points.txt
py_hangman-0.4.dist-info/metadata.json
py_hangman-0.4.dist-info/top_level.txt
